acapy_patched-0.5.6.data/scripts/aca-py
aries_cloudagent/__init__.py
aries_cloudagent/version.py
aries_cloudagent/admin/__init__.py
aries_cloudagent/admin/base_server.py
aries_cloudagent/admin/error.py
aries_cloudagent/admin/server.py
aries_cloudagent/admin/tests/__init__.py
aries_cloudagent/admin/tests/test_admin_server.py
aries_cloudagent/cache/__init__.py
aries_cloudagent/cache/base.py
aries_cloudagent/cache/basic.py
aries_cloudagent/cache/tests/__init__.py
aries_cloudagent/cache/tests/test_basic_cache.py
aries_cloudagent/commands/__init__.py
aries_cloudagent/commands/help.py
aries_cloudagent/commands/provision.py
aries_cloudagent/commands/start.py
aries_cloudagent/commands/tests/__init__.py
aries_cloudagent/commands/tests/test_help.py
aries_cloudagent/commands/tests/test_init.py
aries_cloudagent/commands/tests/test_provision.py
aries_cloudagent/commands/tests/test_start.py
aries_cloudagent/config/__init__.py
aries_cloudagent/config/argparse.py
aries_cloudagent/config/base.py
aries_cloudagent/config/base_context.py
aries_cloudagent/config/default_context.py
aries_cloudagent/config/default_logging_config.ini
aries_cloudagent/config/error.py
aries_cloudagent/config/injection_context.py
aries_cloudagent/config/injector.py
aries_cloudagent/config/ledger.py
aries_cloudagent/config/logging.py
aries_cloudagent/config/provider.py
aries_cloudagent/config/settings.py
aries_cloudagent/config/util.py
aries_cloudagent/config/wallet.py
aries_cloudagent/config/tests/__init__.py
aries_cloudagent/config/tests/test_argparse.py
aries_cloudagent/config/tests/test_default_context.py
aries_cloudagent/config/tests/test_injection_context.py
aries_cloudagent/config/tests/test_injector.py
aries_cloudagent/config/tests/test_ledger.py
aries_cloudagent/config/tests/test_logging.py
aries_cloudagent/config/tests/test_provider.py
aries_cloudagent/config/tests/test_settings.py
aries_cloudagent/config/tests/test_wallet.py
aries_cloudagent/connections/__init__.py
acapy_patched-0.5.6.dist-info/LICENSE
acapy_patched-0.5.6.dist-info/METADATA
acapy_patched-0.5.6.dist-info/NOTICES
acapy_patched-0.5.6.dist-info/WHEEL
acapy_patched-0.5.6.dist-info/top_level.txt
acapy_patched-0.5.6.dist-info/RECORD
